platform_driver/__init__.py
platform_driver/agent.py
platform_driver/config.py
platform_driver/constants.py
platform_driver/equipment.py
platform_driver/overrides.py
platform_driver/poll_scheduler.py
platform_driver/reservations.py
platform_driver/scalability_testing.py
platform_driver/topic_tree.py
volttron-platform-driver-default-vip-id
volttron_platform_driver-2.0.0rc3.dist-info/LICENSE
volttron_platform_driver-2.0.0rc3.dist-info/METADATA
volttron_platform_driver-2.0.0rc3.dist-info/WHEEL
volttron_platform_driver-2.0.0rc3.dist-info/entry_points.txt
volttron_platform_driver-2.0.0rc3.dist-info/RECORD
