Metadata-Version: 2.3
Name: volttron-platform-driver
Version: 2.0.0rc3
Summary: The Platform Driver agent is a special purpose agent that manages communication between the Volttron platform and devices. The Platform driver features a number of endpoints for collecting data and sending control signals using the message bus and automatically publishes data to the bus on a specified interval.
License: Apache-2.0
Author: VOLTTRON Team
Author-email: volttron@pnnl.gov
Requires-Python: >=3.10,<4.0
Classifier: Intended Audience :: Developers
Classifier: Intended Audience :: Information Technology
Classifier: Intended Audience :: Other Audience
Classifier: Intended Audience :: Science/Research
Classifier: License :: OSI Approved :: Apache Software License
Classifier: Programming Language :: Python :: 3
Classifier: Programming Language :: Python :: 3.10
Classifier: Programming Language :: Python :: 3.11
Classifier: Programming Language :: Python :: 3.12
Classifier: Programming Language :: Python :: 3.13
Classifier: Programming Language :: Python :: 3 :: Only
Requires-Dist: treelib (>=1.7.0)
Requires-Dist: volttron-core (>=2.0.0rc0)
Requires-Dist: volttron-lib-base-driver (>=2.0.0rc0)
Project-URL: Homepage, https://github.com/eclipse-volttron/platform-driver-agent
Project-URL: Repository, https://github.com/eclipse-volttron/platform-driver-agent
